bupy/__init__.py
bupy/__main__.py
bupy/butane.py
bupy/cli.py
bupy/fcos.py
bupy/qemu.py
bupy/template.py
bupy/util.py
bupy-0.1.2.dist-info/LICENSE
bupy-0.1.2.dist-info/METADATA
bupy-0.1.2.dist-info/WHEEL
bupy-0.1.2.dist-info/entry_points.txt
bupy-0.1.2.dist-info/RECORD
