Metadata-Version: 2.1
Name: bupy
Version: 0.1.2
Summary: A Python toolkit for Butane and Ignition
Author: QuickVM
Author-email: hello@quickvm.com
Requires-Python: >=3.8.10,<4.0.0
Classifier: Programming Language :: Python :: 3
Classifier: Programming Language :: Python :: 3.9
Classifier: Programming Language :: Python :: 3.10
Classifier: Programming Language :: Python :: 3.11
Requires-Dist: Jinja2 (>=3.1.2,<4.0.0)
Requires-Dist: pip (>=23.0.1,<24.0.0)
Requires-Dist: pyxdg (>=0.28,<0.29)
Requires-Dist: rich (>=13.4.2,<14.0.0)
Requires-Dist: ruamel.yaml (>=0.17.21,<0.18.0)
Requires-Dist: typer[all] (>=0.9.0,<0.10.0)
Requires-Dist: urllib3 (>=1.26.10,<2.0.0)
